[{"name":"twit-api","description":null,"location":"index.html","searchKeys":["twit-api"]},{"name":"factories","description":null,"location":"twit-api/factories/index.html","searchKeys":["factories"]},{"name":"TweetFactory","description":null,"location":"twit-api/factories/-tweet-factory/index.html","searchKeys":["TweetFactory"]},{"name":"models","description":null,"location":"twit-api/models/index.html","searchKeys":["models"]},{"name":"FollowRequestBody","description":null,"location":"twit-api/models/-follow-request-body/index.html","searchKeys":["FollowRequestBody"]},{"name":"SimplifiedTweet","description":null,"location":"twit-api/models/-simplified-tweet/index.html","searchKeys":["SimplifiedTweet"]},{"name":"SimplifiedUser","description":null,"location":"twit-api/models/-simplified-user/index.html","searchKeys":["SimplifiedUser"]},{"name":"Tweet","description":null,"location":"twit-api/models/-tweet/index.html","searchKeys":["Tweet"]},{"name":"TweetType","description":null,"location":"twit-api/models/-tweet-type/index.html","searchKeys":["TweetType"]},{"name":"IMAGE","description":null,"location":"twit-api/models/-tweet-type/-i-m-a-g-e/index.html","searchKeys":["IMAGE"]},{"name":"LINK","description":null,"location":"twit-api/models/-tweet-type/-l-i-n-k/index.html","searchKeys":["LINK"]},{"name":"TEXT","description":null,"location":"twit-api/models/-tweet-type/-t-e-x-t/index.html","searchKeys":["TEXT"]},{"name":"VIDEO","description":null,"location":"twit-api/models/-tweet-type/-v-i-d-e-o/index.html","searchKeys":["VIDEO"]},{"name":"User","description":null,"location":"twit-api/models/-user/index.html","searchKeys":["User"]},{"name":"routes","description":null,"location":"twit-api/routes/index.html","searchKeys":["routes"]},{"name":"UserRouteKt","description":null,"location":"twit-api/routes/-user-route-kt/index.html","searchKeys":["UserRouteKt"]},{"name":"services.v1","description":null,"location":"twit-api/services.v1/index.html","searchKeys":["services.v1"]},{"name":"UserService","description":null,"location":"twit-api/services.v1/-user-service/index.html","searchKeys":["UserService"]},{"name":"UserServiceV1","description":null,"location":"twit-api/services.v1/-user-service-v1/index.html","searchKeys":["UserServiceV1"]},{"name":"twit","description":null,"location":"twit-api/twit/index.html","searchKeys":["twit"]},{"name":"ApplicationKt","description":null,"location":"twit-api/twit/-application-kt/index.html","searchKeys":["ApplicationKt"]},{"name":"utils","description":null,"location":"twit-api/utils/index.html","searchKeys":["utils"]},{"name":"AlreadyExistsException","description":null,"location":"twit-api/utils/-already-exists-exception/index.html","searchKeys":["AlreadyExistsException"]},{"name":"ModelHelpersKt","description":null,"location":"twit-api/utils/-model-helpers-kt/index.html","searchKeys":["ModelHelpersKt"]}]
